marketML/__init__.py
marketML/calc_tools.py
marketML/example.py
marketML/get_binance.py
marketML/performance.py
marketML/plotting.py
marketML/scaler.py
marketML/simple_machine.py
marketML/simulation.py
marketML/stock_sim.py
marketML/synthetic_driver.py
marketML/test.py
marketML/tracking.py
marketml-0.1.2.dist-info/METADATA
marketml-0.1.2.dist-info/WHEEL
marketml-0.1.2.dist-info/top_level.txt
marketml-0.1.2.dist-info/RECORD
