Metadata-Version: 2.4
Name: marketML
Version: 0.1.2
Summary: A lightweight crypto trading and ML toolkit
Author-email: Andrés Huster Zapke <aahuster@gmail.com>
Requires-Python: >=3.0
Requires-Dist: binance==0.3
Requires-Dist: keras==3.8.0
Requires-Dist: matplotlib==3.10.6
Requires-Dist: numpy
Requires-Dist: pandas==2.3.3
Requires-Dist: python_binance==1.0.24
Requires-Dist: scikit_learn==1.7.2
Requires-Dist: scipy==1.16.2
Requires-Dist: tensorflow==2.18.0
